ashraftools/__init__.py
ashraf_tools-1.0.0.dist-info/METADATA
ashraf_tools-1.0.0.dist-info/WHEEL
ashraf_tools-1.0.0.dist-info/license.txt
ashraf_tools-1.0.0.dist-info/top_level.txt
ashraf_tools-1.0.0.dist-info/RECORD
